{
  "merkle_root": [
    2,
    19,
    178,
    254,
    19,
    251,
    223,
    19,
    11,
    9,
    249,
    0,
    179,
    40,
    223,
    102,
    59,
    118,
    105,
    148,
    25,
    207,
    77,
    7,
    83,
    88,
    161,
    113,
    40,
    11,
    70,
    54
  ],
  "airdrop_version": 0,
  "max_num_nodes": 11,
  "max_total_claim": 7213971,
  "tree_nodes": [
    {
      "claimant": [
        32,
        93,
        60,
        105,
        249,
        148,
        0,
        56,
        36,
        48,
        76,
        226,
        5,
        29,
        252,
        105,
        1,
        100,
        191,
        16,
        5,
        59,
        9,
        106,
        121,
        48,
        200,
        52,
        246,
        225,
        21,
        230
      ],
      "amount": 248598,
      "locked_amount": 0,
      "proof": [
        [
          174,
          142,
          60,
          148,
          200,
          193,
          168,
          238,
          186,
          24,
          95,
          15,
          177,
          167,
          86,
          60,
          235,
          70,
          20,
          15,
          113,
          3,
          150,
          212,
          125,
          168,
          12,
          210,
          198,
          182,
          0,
          155
        ],
        [
          21,
          235,
          207,
          138,
          156,
          175,
          199,
          190,
          141,
          223,
          108,
          142,
          40,
          31,
          174,
          163,
          123,
          112,
          238,
          92,
          48,
          51,
          157,
          59,
          46,
          165,
          133,
          164,
          215,
          5,
          134,
          244
        ],
        [
          79,
          42,
          145,
          89,
          101,
          25,
          201,
          252,
          253,
          135,
          176,
          122,
          104,
          45,
          24,
          16,
          153,
          245,
          176,
          185,
          31,
          224,
          87,
          167,
          138,
          241,
          219,
          5,
          168,
          79,
          78,
          195
        ],
        [
          105,
          139,
          184,
          110,
          55,
          182,
          73,
          82,
          190,
          245,
          72,
          29,
          185,
          239,
          150,
          17,
          31,
          251,
          218,
          255,
          178,
          20,
          16,
          148,
          132,
          4,
          30,
          116,
          194,
          77,
          148,
          240
        ]
      ]
    },
    {
      "claimant": [
        43,
        210,
        174,
        50,
        158,
        173,
        247,
        253,
        80,
        15,
        6,
        193,
        62,
        154,
        163,
        191,
        182,
        140,
        222,
        87,
        234,
        30,
        201,
        253,
        33,
        109,
        94,
        89,
        207,
        29,
        122,
        19
      ],
      "amount": 2246,
      "locked_amount": 0,
      "proof": [
        [
          148,
          80,
          232,
          172,
          80,
          222,
          161,
          125,
          238,
          207,
          234,
          102,
          162,
          89,
          195,
          159,
          29,
          11,
          13,
          186,
          171,
          83,
          255,
          120,
          110,
          84,
          171,
          255,
          207,
          199,
          125,
          118
        ],
        [
          21,
          235,
          207,
          138,
          156,
          175,
          199,
          190,
          141,
          223,
          108,
          142,
          40,
          31,
          174,
          163,
          123,
          112,
          238,
          92,
          48,
          51,
          157,
          59,
          46,
          165,
          133,
          164,
          215,
          5,
          134,
          244
        ],
        [
          79,
          42,
          145,
          89,
          101,
          25,
          201,
          252,
          253,
          135,
          176,
          122,
          104,
          45,
          24,
          16,
          153,
          245,
          176,
          185,
          31,
          224,
          87,
          167,
          138,
          241,
          219,
          5,
          168,
          79,
          78,
          195
        ],
        [
          105,
          139,
          184,
          110,
          55,
          182,
          73,
          82,
          190,
          245,
          72,
          29,
          185,
          239,
          150,
          17,
          31,
          251,
          218,
          255,
          178,
          20,
          16,
          148,
          132,
          4,
          30,
          116,
          194,
          77,
          148,
          240
        ]
      ]
    },
    {
      "claimant": [
        49,
        4,
        165,
        10,
        164,
        213,
        10,
        125,
        173,
        160,
        52,
        0,
        253,
        113,
        12,
        38,
        5,
        235,
        203,
        130,
        113,
        18,
        169,
        228,
        27,
        5,
        45,
        164,
        130,
        162,
        150,
        125
      ],
      "amount": 103676,
      "locked_amount": 0,
      "proof": [
        [
          133,
          119,
          44,
          33,
          148,
          92,
          180,
          242,
          110,
          156,
          113,
          38,
          255,
          170,
          85,
          235,
          96,
          161,
          138,
          93,
          176,
          245,
          23,
          174,
          250,
          160,
          198,
          140,
          12,
          165,
          54,
          195
        ],
        [
          234,
          114,
          205,
          236,
          229,
          160,
          49,
          98,
          12,
          210,
          50,
          246,
          121,
          15,
          131,
          56,
          35,
          37,
          131,
          212,
          44,
          12,
          121,
          132,
          53,
          97,
          216,
          89,
          247,
          127,
          53,
          189
        ],
        [
          79,
          42,
          145,
          89,
          101,
          25,
          201,
          252,
          253,
          135,
          176,
          122,
          104,
          45,
          24,
          16,
          153,
          245,
          176,
          185,
          31,
          224,
          87,
          167,
          138,
          241,
          219,
          5,
          168,
          79,
          78,
          195
        ],
        [
          105,
          139,
          184,
          110,
          55,
          182,
          73,
          82,
          190,
          245,
          72,
          29,
          185,
          239,
          150,
          17,
          31,
          251,
          218,
          255,
          178,
          20,
          16,
          148,
          132,
          4,
          30,
          116,
          194,
          77,
          148,
          240
        ]
      ]
    },
    {
      "claimant": [
        76,
        70,
        159,
        71,
        150,
        69,
        101,
        2,
        104,
        14,
        202,
        58,
        30,
        36,
        109,
        68,
        130,
        213,
        125,
        34,
        37,
        148,
        135,
        99,
        156,
        51,
        208,
        98,
        97,
        185,
        144,
        101
      ],
      "amount": 30453,
      "locked_amount": 0,
      "proof": [
        [
          85,
          171,
          180,
          27,
          48,
          21,
          249,
          193,
          81,
          85,
          20,
          189,
          160,
          134,
          217,
          38,
          187,
          24,
          93,
          240,
          237,
          29,
          164,
          183,
          217,
          5,
          183,
          20,
          90,
          122,
          49,
          96
        ],
        [
          234,
          114,
          205,
          236,
          229,
          160,
          49,
          98,
          12,
          210,
          50,
          246,
          121,
          15,
          131,
          56,
          35,
          37,
          131,
          212,
          44,
          12,
          121,
          132,
          53,
          97,
          216,
          89,
          247,
          127,
          53,
          189
        ],
        [
          79,
          42,
          145,
          89,
          101,
          25,
          201,
          252,
          253,
          135,
          176,
          122,
          104,
          45,
          24,
          16,
          153,
          245,
          176,
          185,
          31,
          224,
          87,
          167,
          138,
          241,
          219,
          5,
          168,
          79,
          78,
          195
        ],
        [
          105,
          139,
          184,
          110,
          55,
          182,
          73,
          82,
          190,
          245,
          72,
          29,
          185,
          239,
          150,
          17,
          31,
          251,
          218,
          255,
          178,
          20,
          16,
          148,
          132,
          4,
          30,
          116,
          194,
          77,
          148,
          240
        ]
      ]
    },
    {
      "claimant": [
        111,
        74,
        108,
        136,
        22,
        21,
        74,
        90,
        111,
        48,
        180,
        146,
        138,
        248,
        42,
        25,
        127,
        67,
        157,
        199,
        224,
        213,
        88,
        182,
        206,
        9,
        69,
        243,
        189,
        218,
        106,
        216
      ],
      "amount": 255245,
      "locked_amount": 0,
      "proof": [
        [
          255,
          0,
          205,
          19,
          228,
          38,
          172,
          67,
          88,
          27,
          9,
          142,
          244,
          28,
          152,
          91,
          226,
          51,
          210,
          124,
          18,
          115,
          254,
          183,
          123,
          51,
          30,
          53,
          46,
          75,
          69,
          9
        ],
        [
          180,
          177,
          2,
          173,
          219,
          206,
          32,
          56,
          116,
          237,
          107,
          139,
          204,
          1,
          164,
          218,
          1,
          84,
          53,
          100,
          95,
          178,
          63,
          64,
          33,
          86,
          60,
          16,
          89,
          3,
          70,
          124
        ],
        [
          222,
          142,
          111,
          222,
          114,
          34,
          127,
          93,
          106,
          33,
          250,
          245,
          62,
          55,
          190,
          155,
          163,
          108,
          23,
          133,
          213,
          60,
          228,
          52,
          195,
          221,
          106,
          221,
          38,
          7,
          157,
          101
        ],
        [
          105,
          139,
          184,
          110,
          55,
          182,
          73,
          82,
          190,
          245,
          72,
          29,
          185,
          239,
          150,
          17,
          31,
          251,
          218,
          255,
          178,
          20,
          16,
          148,
          132,
          4,
          30,
          116,
          194,
          77,
          148,
          240
        ]
      ]
    },
    {
      "claimant": [
        113,
        242,
        74,
        209,
        203,
        170,
        89,
        35,
        252,
        210,
        31,
        187,
        252,
        57,
        41,
        177,
        50,
        102,
        188,
        147,
        91,
        79,
        108,
        89,
        168,
        144,
        226,
        14,
        136,
        44,
        61,
        195
      ],
      "amount": 2032172,
      "locked_amount": 0,
      "proof": [
        [
          27,
          153,
          50,
          205,
          198,
          113,
          152,
          56,
          227,
          8,
          23,
          105,
          38,
          197,
          133,
          53,
          124,
          255,
          232,
          73,
          174,
          168,
          237,
          45,
          101,
          119,
          59,
          49,
          219,
          228,
          224,
          165
        ],
        [
          180,
          177,
          2,
          173,
          219,
          206,
          32,
          56,
          116,
          237,
          107,
          139,
          204,
          1,
          164,
          218,
          1,
          84,
          53,
          100,
          95,
          178,
          63,
          64,
          33,
          86,
          60,
          16,
          89,
          3,
          70,
          124
        ],
        [
          222,
          142,
          111,
          222,
          114,
          34,
          127,
          93,
          106,
          33,
          250,
          245,
          62,
          55,
          190,
          155,
          163,
          108,
          23,
          133,
          213,
          60,
          228,
          52,
          195,
          221,
          106,
          221,
          38,
          7,
          157,
          101
        ],
        [
          105,
          139,
          184,
          110,
          55,
          182,
          73,
          82,
          190,
          245,
          72,
          29,
          185,
          239,
          150,
          17,
          31,
          251,
          218,
          255,
          178,
          20,
          16,
          148,
          132,
          4,
          30,
          116,
          194,
          77,
          148,
          240
        ]
      ]
    },
    {
      "claimant": [
        140,
        53,
        92,
        150,
        128,
        71,
        116,
        185,
        133,
        36,
        120,
        44,
        184,
        226,
        50,
        144,
        211,
        236,
        65,
        252,
        26,
        192,
        49,
        198,
        126,
        58,
        14,
        56,
        28,
        17,
        182,
        67
      ],
      "amount": 210311,
      "locked_amount": 0,
      "proof": [
        [
          54,
          28,
          88,
          59,
          30,
          161,
          144,
          44,
          47,
          205,
          89,
          189,
          37,
          233,
          53,
          71,
          243,
          38,
          62,
          97,
          111,
          104,
          101,
          213,
          236,
          214,
          104,
          156,
          239,
          79,
          39,
          54
        ],
        [
          204,
          232,
          39,
          248,
          126,
          159,
          190,
          240,
          70,
          92,
          10,
          241,
          122,
          91,
          192,
          81,
          193,
          238,
          105,
          126,
          197,
          251,
          237,
          53,
          2,
          235,
          80,
          91,
          188,
          247,
          33,
          124
        ],
        [
          222,
          142,
          111,
          222,
          114,
          34,
          127,
          93,
          106,
          33,
          250,
          245,
          62,
          55,
          190,
          155,
          163,
          108,
          23,
          133,
          213,
          60,
          228,
          52,
          195,
          221,
          106,
          221,
          38,
          7,
          157,
          101
        ],
        [
          105,
          139,
          184,
          110,
          55,
          182,
          73,
          82,
          190,
          245,
          72,
          29,
          185,
          239,
          150,
          17,
          31,
          251,
          218,
          255,
          178,
          20,
          16,
          148,
          132,
          4,
          30,
          116,
          194,
          77,
          148,
          240
        ]
      ]
    },
    {
      "claimant": [
        154,
        51,
        157,
        44,
        146,
        166,
        252,
        148,
        149,
        60,
        177,
        94,
        231,
        253,
        46,
        56,
        67,
        195,
        92,
        11,
        119,
        236,
        98,
        91,
        241,
        39,
        34,
        238,
        92,
        239,
        18,
        204
      ],
      "amount": 4318172,
      "locked_amount": 0,
      "proof": [
        [
          177,
          83,
          214,
          187,
          177,
          15,
          204,
          78,
          196,
          181,
          213,
          117,
          22,
          30,
          127,
          33,
          89,
          179,
          126,
          160,
          9,
          18,
          11,
          79,
          59,
          198,
          241,
          193,
          60,
          89,
          94,
          198
        ],
        [
          204,
          232,
          39,
          248,
          126,
          159,
          190,
          240,
          70,
          92,
          10,
          241,
          122,
          91,
          192,
          81,
          193,
          238,
          105,
          126,
          197,
          251,
          237,
          53,
          2,
          235,
          80,
          91,
          188,
          247,
          33,
          124
        ],
        [
          222,
          142,
          111,
          222,
          114,
          34,
          127,
          93,
          106,
          33,
          250,
          245,
          62,
          55,
          190,
          155,
          163,
          108,
          23,
          133,
          213,
          60,
          228,
          52,
          195,
          221,
          106,
          221,
          38,
          7,
          157,
          101
        ],
        [
          105,
          139,
          184,
          110,
          55,
          182,
          73,
          82,
          190,
          245,
          72,
          29,
          185,
          239,
          150,
          17,
          31,
          251,
          218,
          255,
          178,
          20,
          16,
          148,
          132,
          4,
          30,
          116,
          194,
          77,
          148,
          240
        ]
      ]
    },
    {
      "claimant": [
        221,
        168,
        13,
        124,
        40,
        114,
        24,
        141,
        42,
        119,
        33,
        218,
        108,
        196,
        186,
        250,
        92,
        65,
        75,
        0,
        11,
        151,
        185,
        243,
        14,
        177,
        235,
        204,
        215,
        139,
        1,
        136
      ],
      "amount": 4312,
      "locked_amount": 0,
      "proof": [
        [
          101,
          31,
          135,
          184,
          240,
          106,
          126,
          2,
          102,
          53,
          86,
          234,
          170,
          189,
          126,
          184,
          154,
          176,
          233,
          152,
          93,
          187,
          37,
          237,
          140,
          63,
          56,
          55,
          103,
          157,
          236,
          186
        ],
        [
          73,
          157,
          51,
          141,
          199,
          52,
          238,
          214,
          162,
          139,
          70,
          63,
          63,
          61,
          111,
          97,
          161,
          100,
          42,
          228,
          197,
          112,
          90,
          18,
          224,
          199,
          242,
          157,
          156,
          163,
          181,
          138
        ],
        [
          84,
          192,
          165,
          59,
          149,
          38,
          123,
          95,
          5,
          139,
          135,
          103,
          30,
          63,
          4,
          66,
          125,
          79,
          153,
          31,
          207,
          100,
          117,
          118,
          24,
          193,
          112,
          98,
          142,
          206,
          71,
          110
        ],
        [
          27,
          0,
          202,
          14,
          230,
          176,
          178,
          19,
          181,
          182,
          23,
          179,
          188,
          233,
          212,
          81,
          206,
          40,
          104,
          195,
          85,
          57,
          210,
          168,
          40,
          247,
          61,
          115,
          212,
          239,
          216,
          193
        ]
      ]
    },
    {
      "claimant": [
        244,
        22,
        54,
        92,
        107,
        33,
        139,
        85,
        83,
        110,
        112,
        221,
        198,
        116,
        43,
        34,
        229,
        188,
        145,
        28,
        142,
        5,
        135,
        93,
        242,
        65,
        171,
        1,
        45,
        255,
        138,
        234
      ],
      "amount": 7270,
      "locked_amount": 0,
      "proof": [
        [
          105,
          20,
          37,
          234,
          82,
          60,
          171,
          37,
          110,
          103,
          162,
          117,
          247,
          215,
          183,
          143,
          1,
          215,
          111,
          108,
          177,
          18,
          182,
          81,
          43,
          176,
          197,
          134,
          70,
          143,
          143,
          104
        ],
        [
          73,
          157,
          51,
          141,
          199,
          52,
          238,
          214,
          162,
          139,
          70,
          63,
          63,
          61,
          111,
          97,
          161,
          100,
          42,
          228,
          197,
          112,
          90,
          18,
          224,
          199,
          242,
          157,
          156,
          163,
          181,
          138
        ],
        [
          84,
          192,
          165,
          59,
          149,
          38,
          123,
          95,
          5,
          139,
          135,
          103,
          30,
          63,
          4,
          66,
          125,
          79,
          153,
          31,
          207,
          100,
          117,
          118,
          24,
          193,
          112,
          98,
          142,
          206,
          71,
          110
        ],
        [
          27,
          0,
          202,
          14,
          230,
          176,
          178,
          19,
          181,
          182,
          23,
          179,
          188,
          233,
          212,
          81,
          206,
          40,
          104,
          195,
          85,
          57,
          210,
          168,
          40,
          247,
          61,
          115,
          212,
          239,
          216,
          193
        ]
      ]
    },
    {
      "claimant": [
        246,
        165,
        215,
        94,
        66,
        79,
        127,
        234,
        182,
        247,
        215,
        126,
        184,
        116,
        182,
        43,
        110,
        212,
        85,
        136,
        173,
        154,
        21,
        178,
        10,
        147,
        189,
        174,
        231,
        70,
        59,
        193
      ],
      "amount": 1516,
      "locked_amount": 0,
      "proof": [
        [
          9,
          41,
          54,
          240,
          31,
          208,
          94,
          139,
          202,
          69,
          99,
          5,
          39,
          246,
          94,
          243,
          164,
          24,
          1,
          80,
          143,
          132,
          230,
          229,
          168,
          1,
          30,
          217,
          253,
          129,
          177,
          222
        ],
        [
          31,
          18,
          240,
          16,
          185,
          249,
          197,
          62,
          227,
          195,
          117,
          103,
          55,
          186,
          94,
          101,
          86,
          234,
          104,
          173,
          200,
          221,
          215,
          147,
          102,
          192,
          21,
          137,
          90,
          14,
          225,
          126
        ],
        [
          84,
          192,
          165,
          59,
          149,
          38,
          123,
          95,
          5,
          139,
          135,
          103,
          30,
          63,
          4,
          66,
          125,
          79,
          153,
          31,
          207,
          100,
          117,
          118,
          24,
          193,
          112,
          98,
          142,
          206,
          71,
          110
        ],
        [
          27,
          0,
          202,
          14,
          230,
          176,
          178,
          19,
          181,
          182,
          23,
          179,
          188,
          233,
          212,
          81,
          206,
          40,
          104,
          195,
          85,
          57,
          210,
          168,
          40,
          247,
          61,
          115,
          212,
          239,
          216,
          193
        ]
      ]
    }
  ]
}